Workbook

Sheet 単語リスト
A1: 1 | B1: answer | C1: 答える
A2: 2 | B2: ask | C2: たずねる
A3: 3 | B3: become | C3: ～になる
A4: 4 | B4: bring | C4: もってくる
A5: 5 | B5: call | C5: 電話をかける
A6: 6 | B6: catch | C6: 捕まえる
A7: 7 | B7: change | C7: 変わる
A8: 8 | B8: choose | C8: 選ぶ
A9: 9 | B9: come | C9: 来る
A10: 10 | B10: cut | C10: 切る
A11: 11 | B11: feel | C11: 感じる
A12: 12 | B12: find | C12: 見つける
... A117: 117 | B117: number | C117: 数
A118: 118 | B118: zero | C118: 0
A119: 119 | B119: hundred | C119: 100
A120: 120 | B120: first | C120: １番目
A121: 121 | B121: second | C121: ２番目
A122: 122 | B122: evening | C122: 夕方
A123: 123 | B123: month | C123: 月
A124: 124 | B124: today | C124: 今日
A125: 125 | B125: tomorrow | C125: 明日
A126: 126 | B126: week | C126: 週
A127: 127 | B127: weekend | C127: 週末
A128: 128 | B128: yesterday | C128: 昨日
A129: 129 | B129: minute | C129: 分
A130: 130 | B130: date | C130: 日
A131: 131 | B131: holiday | C131: 休日
... A278: 278 | B278: frog | C278: カエル
A279: 279 | B279: thousand | C279: 1000
A280: 280 | B280: third | C280: ３番目
A281: 281 | B281: fourth | C281: ４番目
A282: 282 | B282: fifth | C282: ５番目
A283: 283 | B283: sixth | C283: ６番目
A284: 284 | B284: seventh | C284: ７番目
A285: 285 | B285: eighth | C285: ８番目
A286: 286 | B286: ninth | C286: ９番目
A287: 287 | B287: tenth | C287: １０番目
A288: 288 | B288: eleventh | C288: １１番目
A289: 289 | B289: twelfth | C289: １２番目
A290: 290 | B290: thirteenth | C290: １３番目
A291: 291 | B291: fourteenth | C291: １４番目
... A1070: 1070 | B1070: such | C1070: そのような
A1071: 1071 | B1071: TRUE | C1071: 本当の
A1072: 1072 | B1072: useful | C1072: 役に立つ
A1073: 1073 | B1073: actually | C1073: 実際は
A1074: 1074 | B1074: glad | C1074: うれしい
A1075: 1075 | B1075: local | C1075: 地元の
A1076: 1076 | B1076: especially | C1076: 特に
A1077: 1077 | B1077: never | C1077: 一度も～ない
A1078: 1078 | B1078: afraid | C1078: こわがって
A1079: 1079 | B1079: yet | C1079: もう
A1080: 1080 | B1080: enough | C1080: 十分な
A1081: 1081 | B1081: even | C1081: ～でさえ
A1082: 1082 | B1082: few | C1082: 少しの
A1083: 1083 | B1083: both | C1083: 両方の
... A1850: 1850 | B1850: how to~ | C1850: ～のしかた
A1851: 1851
A1852: 1852
A1853: 1853
A1854: 1854
A1855: 1855
A1856: 1856
A1857: 1857
A1858: 1858
A1859: 1859
A1860: 1860
A1861: 1861
A1862: 1862
... A2000: 2000

Sheet テスト作成用
A1: =RAND() -> 0.53841061 | B1: =RANK(A1,OFFSET($A$1,$L$1-1,0,$L$2-$L$1+1)) -> #N/A | C1: =単語リスト!A1 -> 1 | D1: =単語リスト!B1 -> answer | E1: =単語リスト!C1 -> 答える | F1: 問題はじめ | G1: 単語番号 | H1: 900 | I1: 1 | J1: =VLOOKUP(I1,$B$1:$E$10000,3+$H$3,) -> 世界中で（の） | L1: =H1-300 -> 600
A2: =RAND() -> 0.18980827 | B2: =RANK(A2,OFFSET($A$1,$L$1-1,0,$L$2-$L$1+1)) -> #N/A | C2: =単語リスト!A2 -> 2 | D2: =単語リスト!B2 -> ask | E2: =単語リスト!C2 -> たずねる | F2: 問題終わり | H2: 1000 | I2: 2 | J2: =VLOOKUP(I2,$B$1:$E$10000,3+$H$3,) -> 毎日 | L2: =H2-300 -> 700
A3: =RAND() -> 0.34800452 | B3: =RANK(A3,OFFSET($A$1,$L$1-1,0,$L$2-$L$1+1)) -> #N/A | C3: =単語リスト!A3 -> 3 | D3: =単語リスト!B3 -> become | E3: =単語リスト!C3 -> ～になる | F3: 出題形式 | H3: 1 | I3: 3 | J3: =VLOOKUP(I3,$B$1:$E$10000,3+$H$3,) -> あなたはどうですか。
A4: =RAND() -> 0.73357965 | B4: =RANK(A4,OFFSET($A$1,$L$1-1,0,$L$2-$L$1+1)) -> #N/A | C4: =単語リスト!A4 -> 4 | D4: =単語リスト!B4 -> bring | E4: =単語リスト!C4 -> もってくる | I4: 4 | J4: =VLOOKUP(I4,$B$1:$E$10000,3+$H$3,) -> どういたしまして。
A5: =RAND() -> 0.85585197 | B5: =RANK(A5,OFFSET($A$1,$L$1-1,0,$L$2-$L$1+1)) -> #N/A | C5: =単語リスト!A5 -> 5 | D5: =単語リスト!B5 -> call | E5: =単語リスト!C5 -> 電話をかける | I5: 5 | J5: =VLOOKUP(I5,$B$1:$E$10000,3+$H$3,) -> ～を見る
A6: =RAND() -> 0.21061362 | B6: =RANK(A6,OFFSET($A$1,$L$1-1,0,$L$2-$L$1+1)) -> #N/A | C6: =単語リスト!A6 -> 6 | D6: =単語リスト!B6 -> catch | E6: =単語リスト!C6 -> 捕まえる | I6: 6 | J6: =VLOOKUP(I6,$B$1:$E$10000,3+$H$3,) -> １つ（個、本、枚）の～
A7: =RAND() -> 0.87857245 | B7: =RANK(A7,OFFSET($A$1,$L$1-1,0,$L$2-$L$1+1)) -> #N/A | C7: =単語リスト!A7 -> 7 | D7: =単語リスト!B7 -> change | E7: =単語リスト!C7 -> 変わる | I7: 7 | J7: =VLOOKUP(I7,$B$1:$E$10000,3+$H$3,) -> もちろん
A8: =RAND() -> 0.37136792 | B8: =RANK(A8,OFFSET($A$1,$L$1-1,0,$L$2-$L$1+1)) -> #N/A | C8: =単語リスト!A8 -> 8 | D8: =単語リスト!B8 -> choose | E8: =単語リスト!C8 -> 選ぶ | I8: 8 | J8: =VLOOKUP(I8,$B$1:$E$10000,3+$H$3,) -> 入浴する
A9: =RAND() -> 0.56064905 | B9: =RANK(A9,OFFSET($A$1,$L$1-1,0,$L$2-$L$1+1)) -> #N/A | C9: =単語リスト!A9 -> 9 | D9: =単語リスト!B9 -> come | E9: =単語リスト!C9 -> 来る | I9: 9 | J9: =VLOOKUP(I9,$B$1:$E$10000,3+$H$3,) -> いくつかの～ですか。
A10: =RAND() -> 0.022402995 | B10: =RANK(A10,OFFSET($A$1,$L$1-1,0,$L$2-$L$1+1)) -> #N/A | C10: =単語リスト!A10 -> 10 | D10: =単語リスト!B10 -> cut | E10: =単語リスト!C10 -> 切る | I10: 10 | J10: =VLOOKUP(I10,$B$1:$E$10000,3+$H$3,) -> ～と..の間に（の）
A11: =RAND() -> 0.38350128 | B11: =RANK(A11,OFFSET($A$1,$L$1-1,0,$L$2-$L$1+1)) -> #N/A | C11: =単語リスト!A11 -> 11 | D11: =単語リスト!B11 -> feel | E11: =単語リスト!C11 -> 感じる | I11: 11 | J11: =VLOOKUP(I11,$B$1:$E$10000,3+$H$3,) -> カップ１杯（の量）の～
A12: =RAND() -> 0.52300347 | B12: =RANK(A12,OFFSET($A$1,$L$1-1,0,$L$2-$L$1+1)) -> #N/A | C12: =単語リスト!A12 -> 12 | D12: =単語リスト!B12 -> find | E12: =単語リスト!C12 -> 見つける | I12: 12 | J12: =VLOOKUP(I12,$B$1:$E$10000,3+$H$3,) -> ～はいくらですか。
A13: =RAND() -> 0.94969076 | B13: =RANK(A13,OFFSET($A$1,$L$1-1,0,$L$2-$L$1+1)) -> #N/A | C13: =単語リスト!A13 -> 13 | D13: =単語リスト!B13 -> give | E13: =単語リスト!C13 -> 与える | I13: 13 | J13: =VLOOKUP(I13,$B$1:$E$10000,3+$H$3,) -> ～に満ちている
A14: =RAND() -> 0.90077249 | B14: =RANK(A14,OFFSET($A$1,$L$1-1,0,$L$2-$L$1+1)) -> #N/A | C14: =単語リスト!A14 -> 14 | D14: =単語リスト!B14 -> grow | E14: =単語リスト!C14 -> 育てる | I14: 14 | J14: =VLOOKUP(I14,$B$1:$E$10000,3+$H$3,) -> 宿題をする
A15: =RAND() -> 0.90027744 | B15: =RANK(A15,OFFSET($A$1,$L$1-1,0,$L$2-$L$1+1)) -> #N/A | C15: =単語リスト!A15 -> 15 | D15: =単語リスト!B15 -> hear | E15: =単語リスト!C15 -> 聞く | I15: 15 | J15: =VLOOKUP(I15,$B$1:$E$10000,3+$H$3,) -> 結局
... A50: =RAND() -> 0.31672755 | B50: =RANK(A50,OFFSET($A$1,$L$1-1,0,$L$2-$L$1+1)) -> #N/A | C50: =単語リスト!A50 -> 50 | D50: =単語リスト!B50 -> am | E50: =単語リスト!C50 -> ～である | I50: 50 | J50: =VLOOKUP(I50,$B$1:$E$10000,3+$H$3,) -> ～を楽しみに待つ
A51: =RAND() -> 0.18745182 | B51: =RANK(A51,OFFSET($A$1,$L$1-1,0,$L$2-$L$1+1)) -> #N/A | C51: =単語リスト!A51 -> 51 | D51: =単語リスト!B51 -> are | E51: =単語リスト!C51 -> ～である
A52: =RAND() -> 0.22254599 | B52: =RANK(A52,OFFSET($A$1,$L$1-1,0,$L$2-$L$1+1)) -> #N/A | C52: =単語リスト!A52 -> 52 | D52: =単語リスト!B52 -> is | E52: =単語リスト!C52 -> ～である
A53: =RAND() -> 0.28835555 | B53: =RANK(A53,OFFSET($A$1,$L$1-1,0,$L$2-$L$1+1)) -> #N/A | C53: =単語リスト!A53 -> 53 | D53: =単語リスト!B53 -> be | E53: =単語リスト!C53 -> ～である
A54: =RAND() -> 0.06993003 | B54: =RANK(A54,OFFSET($A$1,$L$1-1,0,$L$2-$L$1+1)) -> #N/A | C54: =単語リスト!A54 -> 54 | D54: =単語リスト!B54 -> do | E54: =単語リスト!C54 -> する
A55: =RAND() -> 0.38235778 | B55: =RANK(A55,OFFSET($A$1,$L$1-1,0,$L$2-$L$1+1)) -> #N/A | C55: =単語リスト!A55 -> 55 | D55: =単語リスト!B55 -> buy | E55: =単語リスト!C55 -> 買う
A56: =RAND() -> 0.88014267 | B56: =RANK(A56,OFFSET($A$1,$L$1-1,0,$L$2-$L$1+1)) -> #N/A | C56: =単語リスト!A56 -> 56 | D56: =単語リスト!B56 -> dance | E56: =単語リスト!C56 -> 踊る
A57: =RAND() -> 0.45096029 | B57: =RANK(A57,OFFSET($A$1,$L$1-1,0,$L$2-$L$1+1)) -> #N/A | C57: =単語リスト!A57 -> 57 | D57: =単語リスト!B57 -> drink | E57: =単語リスト!C57 -> 飲む
A58: =RAND() -> 0.19603974 | B58: =RANK(A58,OFFSET($A$1,$L$1-1,0,$L$2-$L$1+1)) -> #N/A | C58: =単語リスト!A58 -> 58 | D58: =単語リスト!B58 -> eat | E58: =単語リスト!C58 -> 食べる
A59: =RAND() -> 0.74528413 | B59: =RANK(A59,OFFSET($A$1,$L$1-1,0,$L$2-$L$1+1)) -> #N/A | C59: =単語リスト!A59 -> 59 | D59: =単語リスト!B59 -> enjoy | E59: =単語リスト!C59 -> 楽しむ
A60: =RAND() -> 0.23681791 | B60: =RANK(A60,OFFSET($A$1,$L$1-1,0,$L$2-$L$1+1)) -> #N/A | C60: =単語リスト!A60 -> 60 | D60: =単語リスト!B60 -> fly | E60: =単語リスト!C60 -> 飛ぶ
A61: =RAND() -> 0.38098201 | B61: =RANK(A61,OFFSET($A$1,$L$1-1,0,$L$2-$L$1+1)) -> #N/A | C61: =単語リスト!A61 -> 61 | D61: =単語リスト!B61 -> get | E61: =単語リスト!C61 -> 得る
A62: =RAND() -> 0.79009549 | B62: =RANK(A62,OFFSET($A$1,$L$1-1,0,$L$2-$L$1+1)) -> #N/A | C62: =単語リスト!A62 -> 62 | D62: =単語リスト!B62 -> go | E62: =単語リスト!C62 -> 行く
... A76: =RAND() -> 0.057013168 | B76: =RANK(A76,OFFSET($A$1,$L$1-1,0,$L$2-$L$1+1)) -> #N/A | C76: =単語リスト!A76 -> 76 | D76: =単語リスト!B76 -> speak | E76: =単語リスト!C76 -> 話す
A77: =RAND() -> 0.83817165 | B77: =RANK(A77,OFFSET($A$1,$L$1-1,0,$L$2-$L$1+1)) -> #N/A | C77: =単語リスト!A77 -> 77 | D77: =単語リスト!B77 -> stop | E77: 止まる
A78: =RAND() -> 0.21126128 | B78: =RANK(A78,OFFSET($A$1,$L$1-1,0,$L$2-$L$1+1)) -> #N/A | C78: =単語リスト!A78 -> 78 | D78: =単語リスト!B78 -> study | E78: 勉強する
A79: =RAND() -> 0.8906223 | B79: =RANK(A79,OFFSET($A$1,$L$1-1,0,$L$2-$L$1+1)) -> #N/A | C79: =単語リスト!A79 -> 79 | D79: =単語リスト!B79 -> take | E79: 撮る
A80: =RAND() -> 0.12940484 | B80: =RANK(A80,OFFSET($A$1,$L$1-1,0,$L$2-$L$1+1)) -> #N/A | C80: =単語リスト!A80 -> 80 | D80: =単語リスト!B80 -> think | E80: 思う
A81: =RAND() -> 0.96458672 | B81: =RANK(A81,OFFSET($A$1,$L$1-1,0,$L$2-$L$1+1)) -> #N/A | C81: =単語リスト!A81 -> 81 | D81: =単語リスト!B81 -> walk | E81: 歩く
A82: =RAND() -> 0.42589563 | B82: =RANK(A82,OFFSET($A$1,$L$1-1,0,$L$2-$L$1+1)) -> #N/A | C82: =単語リスト!A82 -> 82 | D82: =単語リスト!B82 -> wash | E82: 洗う
A83: =RAND() -> 0.81631902 | B83: =RANK(A83,OFFSET($A$1,$L$1-1,0,$L$2-$L$1+1)) -> #N/A | C83: =単語リスト!A83 -> 83 | D83: =単語リスト!B83 -> cook | E83: =単語リスト!C83 -> 料理する
A84: =RAND() -> 0.61050626 | B84: =RANK(A84,OFFSET($A$1,$L$1-1,0,$L$2-$L$1+1)) -> #N/A | C84: =単語リスト!A84 -> 84 | D84: =単語リスト!B84 -> want | E84: =単語リスト!C84 -> ほしい
A85: =RAND() -> 0.60675338 | B85: =RANK(A85,OFFSET($A$1,$L$1-1,0,$L$2-$L$1+1)) -> #N/A | C85: =単語リスト!A85 -> 85 | D85: =単語リスト!B85 -> join | E85: =単語リスト!C85 -> 加わる
A86: =RAND() -> 0.18542438 | B86: =RANK(A86,OFFSET($A$1,$L$1-1,0,$L$2-$L$1+1)) -> #N/A | C86: =単語リスト!A86 -> 86 | D86: =単語リスト!B86 -> stand | E86: =単語リスト!C86 -> 立つ
A87: =RAND() -> 0.45549112 | B87: =RANK(A87,OFFSET($A$1,$L$1-1,0,$L$2-$L$1+1)) -> #N/A | C87: =単語リスト!A87 -> 87 | D87: =単語リスト!B87 -> try | E87: =単語リスト!C87 -> 試す
A88: =RAND() -> 0.083781354 | B88: =RANK(A88,OFFSET($A$1,$L$1-1,0,$L$2-$L$1+1)) -> #N/A | C88: =単語リスト!A88 -> 88 | D88: =単語リスト!B88 -> fall | E88: =単語リスト!C88 -> 落ちる
A89: =RAND() -> 0.051211082 | B89: =RANK(A89,OFFSET($A$1,$L$1-1,0,$L$2-$L$1+1)) -> #N/A | C89: =単語リスト!A89 -> 89 | D89: =単語リスト!B89 -> save | E89: =単語リスト!C89 -> 節約する
A90: =RAND() -> 0.48169735 | B90: =RANK(A90,OFFSET($A$1,$L$1-1,0,$L$2-$L$1+1)) -> #N/A | C90: =単語リスト!A90 -> 90 | D90: =単語リスト!B90 -> pick | E90: =単語リスト!C90 -> 摘む
A91: =RAND() -> 0.92513282 | B91: =RANK(A91,OFFSET($A$1,$L$1-1,0,$L$2-$L$1+1)) -> #N/A | C91: =単語リスト!A91 -> 91 | D91: =単語リスト!B91 -> travel | E91: =単語リスト!C91 -> 旅行する
A92: =RAND() -> 0.1950173 | B92: =RANK(A92,OFFSET($A$1,$L$1-1,0,$L$2-$L$1+1)) -> #N/A | C92: =単語リスト!A92 -> 92 | D92: =単語リスト!B92 -> guess | E92: =単語リスト!C92 -> 推測する
A93: =RAND() -> 0.3537849 | B93: =RANK(A93,OFFSET($A$1,$L$1-1,0,$L$2-$L$1+1)) -> #N/A | C93: =単語リスト!A93 -> 93 | D93: =単語リスト!B93 -> draw | E93: =単語リスト!C93 -> かく
A94: =RAND() -> 0.5678766 | B94: =RANK(A94,OFFSET($A$1,$L$1-1,0,$L$2-$L$1+1)) -> #N/A | C94: =単語リスト!A94 -> 94 | D94: =単語リスト!B94 -> ride | E94: =単語リスト!C94 -> 乗る
A95: =RAND() -> 0.91031045 | B95: =RANK(A95,OFFSET($A$1,$L$1-1,0,$L$2-$L$1+1)) -> #N/A | C95: =単語リスト!A95 -> 95 | D95: =単語リスト!B95 -> sit | E95: =単語リスト!C95 -> 座る
A96: =RAND() -> 0.1821606 | B96: =RANK(A96,OFFSET($A$1,$L$1-1,0,$L$2-$L$1+1)) -> #N/A | C96: =単語リスト!A96 -> 96 | D96: =単語リスト!B96 -> swim | E96: 泳ぐ
A97: =RAND() -> 0.71581308 | B97: =RANK(A97,OFFSET($A$1,$L$1-1,0,$L$2-$L$1+1)) -> #N/A | C97: =単語リスト!A97 -> 97 | D97: =単語リスト!B97 -> perform | E97: 演じる
A98: =RAND() -> 0.20632673 | B98: =RANK(A98,OFFSET($A$1,$L$1-1,0,$L$2-$L$1+1)) -> #N/A | C98: =単語リスト!A98 -> 98 | D98: =単語リスト!B98 -> ski | E98: スキーする
A99: =RAND() -> 0.82791293 | B99: =RANK(A99,OFFSET($A$1,$L$1-1,0,$L$2-$L$1+1)) -> #N/A | C99: =単語リスト!A99 -> 99 | D99: =単語リスト!B99 -> pardon | E99: 許す
A100: =RAND() -> 0.076996589 | B100: =RANK(A100,OFFSET($A$1,$L$1-1,0,$L$2-$L$1+1)) -> #N/A | C100: =単語リスト!A100 -> 100 | D100: =単語リスト!B100 -> trust | E100: =単語リスト!C100 -> 信頼する
A101: =RAND() -> 0.076001223 | B101: =RANK(A101,OFFSET($A$1,$L$1-1,0,$L$2-$L$1+1)) -> #N/A | C101: =単語リスト!A101 -> 101 | D101: =単語リスト!B101 -> cheer | E101: =単語リスト!C101 -> 元気づける
A102: =RAND() -> 0.72016461 | B102: =RANK(A102,OFFSET($A$1,$L$1-1,0,$L$2-$L$1+1)) -> #N/A | C102: =単語リスト!A102 -> 102 | D102: =単語リスト!B102 -> reach | E102: =単語リスト!C102 -> 着く
A103: =RAND() -> 0.54159723 | B103: =RANK(A103,OFFSET($A$1,$L$1-1,0,$L$2-$L$1+1)) -> #N/A | C103: =単語リスト!A103 -> 103 | D103: =単語リスト!B103 -> disappear | E103: =単語リスト!C103 -> 見えなくなる
A104: =RAND() -> 0.48521678 | B104: =RANK(A104,OFFSET($A$1,$L$1-1,0,$L$2-$L$1+1)) -> #N/A | C104: =単語リスト!A104 -> 104 | D104: =単語リスト!B104 -> shoot | E104: =単語リスト!C104 -> 撃つ
A105: =RAND() -> 0.021903647 | B105: =RANK(A105,OFFSET($A$1,$L$1-1,0,$L$2-$L$1+1)) -> #N/A | C105: =単語リスト!A105 -> 105 | D105: =単語リスト!B105 -> skate | E105: =単語リスト!C105 -> スケートをする
A106: =RAND() -> 0.78029297 | B106: =RANK(A106,OFFSET($A$1,$L$1-1,0,$L$2-$L$1+1)) -> #N/A | C106: =単語リスト!A106 -> 106 | D106: =単語リスト!B106 -> surf | E106: =単語リスト!C106 -> 見て回る
A107: =RAND() -> 0.68130813 | B107: =RANK(A107,OFFSET($A$1,$L$1-1,0,$L$2-$L$1+1)) -> #N/A | C107: =単語リスト!A107 -> 107 | D107: =単語リスト!B107 -> jump | E107: =単語リスト!C107 -> 跳ぶ
A108: =RAND() -> 0.39345579 | B108: =RANK(A108,OFFSET($A$1,$L$1-1,0,$L$2-$L$1+1)) -> #N/A | C108: =単語リスト!A108 -> 108 | D108: =単語リスト!B108 -> leave | E108: =単語リスト!C108 -> 去る
A109: =RAND() -> 0.28212684 | B109: =RANK(A109,OFFSET($A$1,$L$1-1,0,$L$2-$L$1+1)) -> #N/A | C109: =単語リスト!A109 -> 109 | D109: =単語リスト!B109 -> chat | E109: =単語リスト!C109 -> おしゃべりする
A110: =RAND() -> 0.10936711 | B110: =RANK(A110,OFFSET($A$1,$L$1-1,0,$L$2-$L$1+1)) -> #N/A | C110: =単語リスト!A110 -> 110 | D110: =単語リスト!B110 -> cross | E110: =単語リスト!C110 -> 横断する
A111: =RAND() -> 0.23742679 | B111: =RANK(A111,OFFSET($A$1,$L$1-1,0,$L$2-$L$1+1)) -> #N/A | C111: =単語リスト!A111 -> 111 | D111: =単語リスト!B111 -> relax | E111: =単語リスト!C111 -> くつろぐ
... A1987: =RAND() -> 0.6616004 | B1987: =RANK(A1987,OFFSET($A$1,$L$1-1,0,$L$2-$L$1+1)) -> #N/A | C1987: =単語リスト!A1987 -> 1987 | D1987: =単語リスト!B1987 -> 0 | E1987: =単語リスト!C1987 -> 0

Sheet 出力シート20問
A3: (1) | B3: =テスト作成用!J1 -> 世界中で（の）
A4: (2) | B4: =テスト作成用!J2 -> 毎日
A5: (3) | B5: =テスト作成用!J3 -> あなたはどうですか。
A6: (4) | B6: =テスト作成用!J4 -> どういたしまして。
A7: (5) | B7: =テスト作成用!J5 -> ～を見る
A8: (6) | B8: =テスト作成用!J6 -> １つ（個、本、枚）の～
A9: (7) | B9: =テスト作成用!J7 -> もちろん
A10: (8) | B10: =テスト作成用!J8 -> 入浴する
A11: (9) | B11: =テスト作成用!J9 -> いくつかの～ですか。
A12: (10) | B12: =テスト作成用!J10 -> ～と..の間に（の）
A13: (11) | B13: =テスト作成用!J11 -> カップ１杯（の量）の～
A14: (12) | B14: =テスト作成用!J12 -> ～はいくらですか。
... A18: (16) | B18: =テスト作成用!J16 -> 家で（に）
A19: (17) | B19: =テスト作成用!J17 -> たくさんの～ | G19: /20
A20: (18) | B20: =テスト作成用!J18 -> いいえ、けっこうです。
A21: (19) | B21: =テスト作成用!J19 -> はい、どうぞ。
A22: (20) | B22: =テスト作成用!J20 -> これが～です。
E23: 氏名

Sheet 出力シート30問
A3: (1) | B3: =テスト作成用!J1 -> 世界中で（の）
A4: (2) | B4: =テスト作成用!J2 -> 毎日
A5: (3) | B5: =テスト作成用!J3 -> あなたはどうですか。
A6: (4) | B6: =テスト作成用!J4 -> どういたしまして。
A7: (5) | B7: =テスト作成用!J5 -> ～を見る
A8: (6) | B8: =テスト作成用!J6 -> １つ（個、本、枚）の～
A9: (7) | B9: =テスト作成用!J7 -> もちろん
A10: (8) | B10: =テスト作成用!J8 -> 入浴する
A11: (9) | B11: =テスト作成用!J9 -> いくつかの～ですか。
A12: (10) | B12: =テスト作成用!J10 -> ～と..の間に（の）
A13: (11) | B13: =テスト作成用!J11 -> カップ１杯（の量）の～
A14: (12) | B14: =テスト作成用!J12 -> ～はいくらですか。
... A32: (30) | B32: =テスト作成用!J30 -> 拾い上げる
B34: 氏名 | H34: /30
